py_1151/__init__.py
py_1151/client.py
py_1151-0.1.8.dist-info/METADATA
py_1151-0.1.8.dist-info/WHEEL
py_1151-0.1.8.dist-info/top_level.txt
py_1151-0.1.8.dist-info/RECORD
