Metadata-Version: 2.4
Name: py-1151
Version: 0.1.8
Summary: 1151 API
Author-email: "1151 Inc." <sdk@1151.to>
License: Proprietary
Keywords: 1151
Classifier: Programming Language :: Python :: 3
Classifier: Programming Language :: Python :: 3 :: Only
Classifier: Programming Language :: Python :: 3.9
Classifier: Programming Language :: Python :: 3.10
Classifier: Programming Language :: Python :: 3.11
Classifier: Programming Language :: Python :: 3.12
Classifier: License :: Other/Proprietary License
Classifier: Operating System :: OS Independent
Requires-Python: >=3.9
Requires-Dist: requests>=2.28
